anaiza_effect/__init__.py
anaiza_effect/anaiza.py
anaiza_effect-1.0.0.dist-info/METADATA
anaiza_effect-1.0.0.dist-info/WHEEL
anaiza_effect-1.0.0.dist-info/top_level.txt
anaiza_effect-1.0.0.dist-info/RECORD
